altapay/__init__.py
altapay/api.py
altapay/callback.py
altapay/chargeback.py
altapay/exceptions.py
altapay/funding.py
altapay/payment.py
altapay/resource.py
altapay/transaction.py
altapay/utils.py
altapay-1.4.1.dist-info/LICENSE
altapay-1.4.1.dist-info/METADATA
altapay-1.4.1.dist-info/WHEEL
altapay-1.4.1.dist-info/top_level.txt
altapay-1.4.1.dist-info/RECORD
