Metadata-Version: 2.1
Name: altapay
Version: 1.4.1
Summary: Unofficial Python SDK for Valitor (formerly AltaPay/Pensio).
Home-page: https://github.com/coolshop-com/AltaPay
Author: Coolshop.com
Author-email: altapaysdk@coolshop.com
License: MIT
Platform: UNKNOWN
Classifier: Environment :: Web Environment
Classifier: Intended Audience :: Developers
Classifier: License :: OSI Approved :: MIT License
Classifier: Operating System :: OS Independent
Classifier: Programming Language :: Python
Classifier: Programming Language :: Python :: 3
Classifier: Programming Language :: Python :: 3.5
Classifier: Programming Language :: Python :: 3.6
Classifier: Programming Language :: Python :: 3.7
Requires-Dist: requests
Requires-Dist: six
